Metadata-Version: 2.1
Name: gaugedetect
Version: 0.0.2
Summary: UNKNOWN
Home-page: https://github.com/pannawatr/gaugedetect
Author: 
Author-email: 
License: the8thfloor
Platform: UNKNOWN
